orphos-0.1.0.dist-info/METADATA
orphos-0.1.0.dist-info/WHEEL
orphos/__init__.py
orphos/orphos.cpython-310-x86_64-linux-gnu.so
orphos-0.1.0.dist-info/RECORD
