Metadata-Version: 2.4
Name: orphos
Version: 0.1.0
Classifier: Development Status :: 4 - Beta
Classifier: Intended Audience :: Science/Research
Classifier: License :: OSI Approved :: GNU General Public License v3 or later (GPLv3+)
Classifier: Programming Language :: Python :: 3
Classifier: Programming Language :: Python :: 3.8
Classifier: Programming Language :: Python :: 3.9
Classifier: Programming Language :: Python :: 3.10
Classifier: Programming Language :: Python :: 3.11
Classifier: Programming Language :: Python :: 3.12
Classifier: Programming Language :: Rust
Classifier: Topic :: Scientific/Engineering :: Bio-Informatics
Summary: Python bindings for Orphos - a gene prediction tool for microbial genomes
Keywords: bioinformatics,genomics,gene-prediction,orphos
Author: Orphos Contributors
License: GPL-3.0-or-later
Requires-Python: >=3.8
Project-URL: Homepage, https://github.com/FullHuman/orphos
Project-URL: Repository, https://github.com/FullHuman/orphos
